IbmDeveloperworksQuanbuJiaochengErFix1/README.md
IbmDeveloperworksQuanbuJiaochengErFix1/__init__.py
IbmDeveloperworksQuanbuJiaochengErFix1/__main__.py
IbmDeveloperworksQuanbuJiaochengErFix1/file.epub
IbmDeveloperworksQuanbuJiaochengErFix1/index.html
IbmDeveloperworksQuanbuJiaochengErFix1/css/__init__.py
IbmDeveloperworksQuanbuJiaochengErFix1/css/annotations.css
IbmDeveloperworksQuanbuJiaochengErFix1/css/main.css
IbmDeveloperworksQuanbuJiaochengErFix1/css/normalize.css
IbmDeveloperworksQuanbuJiaochengErFix1/css/popup.css
IbmDeveloperworksQuanbuJiaochengErFix1/font/__init__.py
IbmDeveloperworksQuanbuJiaochengErFix1/font/fontello.eot
IbmDeveloperworksQuanbuJiaochengErFix1/font/fontello.svg
IbmDeveloperworksQuanbuJiaochengErFix1/font/fontello.ttf
IbmDeveloperworksQuanbuJiaochengErFix1/font/fontello.woff
IbmDeveloperworksQuanbuJiaochengErFix1/img/__init__.py
IbmDeveloperworksQuanbuJiaochengErFix1/img/annotator-glyph-sprite.png
IbmDeveloperworksQuanbuJiaochengErFix1/img/annotator-icon-sprite.png
IbmDeveloperworksQuanbuJiaochengErFix1/img/apple-touch-icon.png
IbmDeveloperworksQuanbuJiaochengErFix1/img/cancelfullscreen.png
IbmDeveloperworksQuanbuJiaochengErFix1/img/close.png
IbmDeveloperworksQuanbuJiaochengErFix1/img/fullscreen.png
IbmDeveloperworksQuanbuJiaochengErFix1/img/loader.gif
IbmDeveloperworksQuanbuJiaochengErFix1/img/menu-icon.png
IbmDeveloperworksQuanbuJiaochengErFix1/img/save.png
IbmDeveloperworksQuanbuJiaochengErFix1/img/saved.png
IbmDeveloperworksQuanbuJiaochengErFix1/img/settings-s.png
IbmDeveloperworksQuanbuJiaochengErFix1/img/settings.png
IbmDeveloperworksQuanbuJiaochengErFix1/img/star.png
IbmDeveloperworksQuanbuJiaochengErFix1/js/__init__.py
IbmDeveloperworksQuanbuJiaochengErFix1/js/epub.js
IbmDeveloperworksQuanbuJiaochengErFix1/js/epub.min.js
IbmDeveloperworksQuanbuJiaochengErFix1/js/epub.min.map
IbmDeveloperworksQuanbuJiaochengErFix1/js/hooks.min.js
IbmDeveloperworksQuanbuJiaochengErFix1/js/hooks.min.map
ibm_developerworks_quanbu_jiaocheng_er_fix1-2025.3.25.0.dist-info/METADATA
ibm_developerworks_quanbu_jiaocheng_er_fix1-2025.3.25.0.dist-info/WHEEL
ibm_developerworks_quanbu_jiaocheng_er_fix1-2025.3.25.0.dist-info/entry_points.txt
ibm_developerworks_quanbu_jiaocheng_er_fix1-2025.3.25.0.dist-info/top_level.txt
ibm_developerworks_quanbu_jiaocheng_er_fix1-2025.3.25.0.dist-info/RECORD
